twopilabs/utils/usbtmc/__init__.py
twopilabs/utils/usbtmc/usbtmc_base.py
twopilabs/utils/usbtmc/usbtmc_device.py
twopilabs/utils/usbtmc/usbtmc_device_address.py
twopilabs/utils/usbtmc/usbtmc_device_info.py
twopilabs/utils/usbtmc/usbtmc_exception.py
twopilabs_utils_usbtmc-0.1.7.dist-info/licenses/LICENSE
twopilabs_utils_usbtmc-0.1.7.dist-info/METADATA
twopilabs_utils_usbtmc-0.1.7.dist-info/WHEEL
twopilabs_utils_usbtmc-0.1.7.dist-info/top_level.txt
twopilabs_utils_usbtmc-0.1.7.dist-info/RECORD
