Metadata-Version: 2.4
Name: twopilabs-utils-usbtmc
Version: 0.1.7
Summary: Native generic USB Test and Measurement Class (USBTMC) implementation using PyUSB
Home-page: https://www.2pi-labs.com
Author: 2pi-Labs GmbH
Author-email: opensource@2pi-labs.com
License: LGPLv3
Classifier: License :: OSI Approved :: GNU Lesser General Public License v3 (LGPLv3)
Classifier: Programming Language :: Python :: 3
Requires-Python: >=3.6
License-File: LICENSE
Requires-Dist: pyusb
Requires-Dist: libusb
Dynamic: license-file
